protected_files/__init__.py
protected_files/apps.py
protected_files/fields.py
protected_files/storages.py
protected_files/tests.py
protected_files/urls.py
protected_files/views.py
protected_files/migrations/__init__.py
django_protected_files-2019.1.dist-info/LICENSE
django_protected_files-2019.1.dist-info/METADATA
django_protected_files-2019.1.dist-info/WHEEL
django_protected_files-2019.1.dist-info/top_level.txt
django_protected_files-2019.1.dist-info/RECORD
